matha/__init__.py
matha/algebra.py
matha/basic.py
matha/calculas.py
matha/complex.py
matha/constants.py
matha/geometry.py
matha/graph.py
matha/linalg.py
matha/machine_learning.py
matha/numTheory.py
matha/regression.py
matha/solvers.py
matha/sort.py
matha/special_functions.py
matha/stats.py
matha/trigonometry.py
matha/vector.py
matha_lib-1.2.0.dist-info/licenses/LICENSE
matha_lib-1.2.0.dist-info/METADATA
matha_lib-1.2.0.dist-info/WHEEL
matha_lib-1.2.0.dist-info/top_level.txt
matha_lib-1.2.0.dist-info/RECORD
