Metadata-Version: 2.4
Name: matha-lib
Version: 1.2.0
Summary: A universal math library for Python: Math All Utilities.
Author: AstroJr0
License: MIT
Project-URL: Homepage, https://github.com/AstroJr0/matha-lib
Project-URL: Bug Tracker, https://github.com/AstroJr0/matha-lib/issues
Classifier: Programming Language :: Python :: 3
Classifier: License :: OSI Approved :: MIT License
Classifier: Operating System :: OS Independent
Requires-Python: >=3.10
License-File: LICENSE
Requires-Dist: numpy>=1.26.0
Requires-Dist: scipy>=1.11.0
Requires-Dist: matplotlib>=3.8.0
Dynamic: license-file
